{
  "config": {
    "step": {
      "playlists": {
        "title": "Select playlists",
        "description": "Choose which playlists should get their own entities.",
        "data": {
          "selected_playlist_ids": "Playlists"
        }
      }
    }
  },
  "options": {
    "step": {
      "init": {
        "title": "Select playlists",
        "description": "Choose which playlists should get their own entities.",
        "data": {
          "selected_playlist_ids": "Playlists"
        }
      }
    }
  }
}
